aida/__init__.py
aida/branching.py
aida/choices.py
aida/core.py
aida/lang.py
aida_lib-0.3.0.dist-info/LICENSE
aida_lib-0.3.0.dist-info/WHEEL
aida_lib-0.3.0.dist-info/METADATA
aida_lib-0.3.0.dist-info/RECORD
