Metadata-Version: 2.1
Name: aida-lib
Version: 0.3.0
Summary: Aida is a language agnostic library for text generation.
License: MIT
Author: Giulio Bottari
Author-email: giuliobottari@gmail.com
Requires-Python: >=3.6,<4.0
Classifier: Intended Audience :: Developers
Classifier: License :: OSI Approved :: MIT License
Classifier: Programming Language :: Python :: 3
Classifier: Programming Language :: Python :: 3.6
Classifier: Programming Language :: Python :: 3.7
Classifier: Programming Language :: Python :: 3.8
Project-URL: Bus Tracker, https://github.com/mediatechlab/aida-lib/issues
Project-URL: Documentation, https://github.com/mediatechlab/aida-lib/blob/master/README.md
Project-URL: Source Code, https://github.com/mediatechlab/aida-lib
